twitch_game_notify-0.0.1.dist-info/METADATA
twitch_game_notify-0.0.1.dist-info/RECORD
twitch_game_notify-0.0.1.dist-info/WHEEL
twitch_game_notify-0.0.1.dist-info/entry_points.txt
twitch_game_notify-0.0.1.dist-info/top_level.txt
twitchgamenotify/__init__.py
twitchgamenotify/cache.py
twitchgamenotify/configuration.py
twitchgamenotify/constants.py
twitchgamenotify/main.py
twitchgamenotify/notifications.py
twitchgamenotify/twitch_api.py
twitchgamenotify/version.py
