Metadata-Version: 2.1
Name: twitch-game-notify
Version: 0.0.1
Summary: get notified when your favourite Twitch streamers play your favourite games
Home-page: https://github.com/mwiens91/twitch-game-notify
Author: Matt Wiens
Author-email: mwiens91@gmail.com
License: MIT
Platform: UNKNOWN
Classifier: Development Status :: 4 - Beta
Classifier: Intended Audience :: End Users/Desktop
Classifier: License :: OSI Approved :: MIT License
Classifier: Natural Language :: English
Classifier: Operating System :: Unix
Classifier: Programming Language :: Python :: 3 :: Only
Requires-Dist: dbus-python
Requires-Dist: PyYAML
Requires-Dist: requests
Requires-Dist: xdg
